{
  "id": "delivery_1755066195",
  "title": "Cargo Delivery Contract",
  "description": "Transport valuable cargo to specified destination",
  "mission_type": "delivery",
  "location": "helios_solar_array",
  "faction": "traders_guild",
  "reward_package_id": 4,
  "client": "Traders Guild Representative",
  "state": "Mentioned",
  "is_botched": false,
  "objectives": [
    {
      "id": "1",
      "description": "Pick up medical_supplies from terra_prime",
      "is_achieved": false,
      "is_optional": false,
      "is_ordered": true,
      "achieved_at": null
    },
    {
      "id": "2",
      "description": "Deliver cargo to mining_station_alpha",
      "is_achieved": false,
      "is_optional": false,
      "is_ordered": true,
      "achieved_at": null
    },
    {
      "id": "3",
      "description": "Maintain cargo integrity above 90%",
      "is_achieved": false,
      "is_optional": true,
      "is_ordered": false,
      "achieved_at": null
    }
  ],
  "created_at": "2025-08-13T06:23:15.809596+00:00",
  "updated_at": "2025-08-13T06:23:15.809647+00:00",
  "custom_fields": {
    "cargo_type": "medical_supplies",
    "pickup_location": "terra_prime",
    "delivery_location": "mining_station_alpha",
    "cargo_value": 5000,
    "cargo_mass": 50,
    "time_limit": 7200,
    "cargo_fragile": true,
    "delivery_bonus": 750,
    "reputation_gain": 15
  },
  "triggers": {
    "on_accept": "reserve_cargo_bay",
    "on_pickup": "load_cargo_manifest",
    "on_delivery": "process_payment",
    "on_complete": "update_trader_reputation"
  },
  "progress": {
    "state": "Mentioned",
    "is_botched": false,
    "total_objectives": 3,
    "achieved_objectives": 0,
    "required_objectives": 2,
    "achieved_required": 0,
    "completion_percentage": 0.0
  }
}